{
    "defaults" : {
        "unit" : "inch",
        "tool_diameter" : "0.125",
        "feed_rate" : "30",
        "scale" : "1.000",
        "retract_spindle_to" : "0.50",
        "stock_depth" : "0.1875",
        "step_down" : "0.08"
    },
    "border" : {
        "shape" : "none",
        "wide" : "32.000",
        "tall" : "15.000"
    },
    "cuts" : {
      "0" : {
         "shape" : "drill",
         "outside_diameter" : "0.125" ,
         "bottom" : "-0.2" ,
         "top" : "0.000",
         "x" : "0",
         "y" : "0",
         "array" : {
            "columns" : "2",
            "x_spacing" : "0.5",
            "rows" : "8",
            "y_spacing" : "0.50"
         }
      },
      "2" : {
         "shape" : "drill",
         "inside_diameter" : "0.325" ,
         "bottom" : "-0.2" ,
         "top" : "0.000",
         "x" : "0",
         "y" : "0",
         "array" : {
            "columns" : "2",
            "x_spacing" : "0.5",
            "rows" : "8",
            "y_spacing" : "0.50"
         }
      }
    }
}